fstd2nc.py
fstd2nc_deps/rpnstd.py
fstd2nc_deps/Fstdc.py
fstd2nc_deps/__init__.py
fstd2nc_deps/rpn_helpers.py
fstd2nc_deps/rpnpy/rpndate.py
fstd2nc_deps/rpnpy/ftnnml.py
fstd2nc_deps/rpnpy/openanything.py
fstd2nc_deps/rpnpy/__init__.py
fstd2nc_deps/rpnpy/version.py
fstd2nc_deps/rpnpy/_sharedlibs/libgfortran.so.3
fstd2nc_deps/rpnpy/_sharedlibs/librmnshared_016.2-rpnpy.so
fstd2nc_deps/rpnpy/_sharedlibs/libdescripshared_6.1.10.so
fstd2nc_deps/rpnpy/_sharedlibs/__init__.py
fstd2nc_deps/rpnpy/vgd/all.py
fstd2nc_deps/rpnpy/vgd/proto.py
fstd2nc_deps/rpnpy/vgd/const.py
fstd2nc_deps/rpnpy/vgd/__init__.py
fstd2nc_deps/rpnpy/vgd/base.py
fstd2nc_deps/rpnpy/librmn/all.py
fstd2nc_deps/rpnpy/librmn/proto.py
fstd2nc_deps/rpnpy/librmn/const.py
fstd2nc_deps/rpnpy/librmn/interp.py
fstd2nc_deps/rpnpy/librmn/__init__.py
fstd2nc_deps/rpnpy/librmn/base.py
fstd2nc_deps/rpnpy/librmn/grids.py
fstd2nc_deps/rpnpy/librmn/fstd98.py
fstd2nc_deps/rpnpy/utils/llacar.py
fstd2nc_deps/rpnpy/utils/__init__.py
fstd2nc-0.20170427.1.dist-info/metadata.json
fstd2nc-0.20170427.1.dist-info/WHEEL
fstd2nc-0.20170427.1.dist-info/DESCRIPTION.rst
fstd2nc-0.20170427.1.dist-info/METADATA
fstd2nc-0.20170427.1.dist-info/top_level.txt
fstd2nc-0.20170427.1.dist-info/RECORD
fstd2nc-0.20170427.1.dist-info/entry_points.txt
