Metadata-Version: 2.0
Name: fstd2nc
Version: 0.20170427.1
Summary: Converts FSTD files (from Environment Canada) to netCDF files.
Home-page: https://github.com/neishm/fstd2nc
Author: Mike Neish
Author-email: UNKNOWN
License: LGPL-3
Keywords: fstd2nc rpnpy
Platform: UNKNOWN
Classifier: Development Status :: 3 - Alpha
Classifier: Environment :: Console
Classifier: Intended Audience :: Science/Research
Classifier: License :: OSI Approved :: GNU Lesser General Public License v3 (LGPLv3)
Classifier: Operating System :: POSIX :: Linux
Classifier: Operating System :: Microsoft :: Windows
Classifier: Programming Language :: Python :: 2.7
Classifier: Topic :: Scientific/Engineering :: Atmospheric Science
Requires-Dist: netcdf4
Requires-Dist: numpy
Requires-Dist: pytz
